spectre/__init__.py
spectre-0.0.1.dist-info/DESCRIPTION.rst
spectre-0.0.1.dist-info/METADATA
spectre-0.0.1.dist-info/RECORD
spectre-0.0.1.dist-info/WHEEL
spectre-0.0.1.dist-info/entry_points.txt
spectre-0.0.1.dist-info/metadata.json
spectre-0.0.1.dist-info/top_level.txt
