Metadata-Version: 2.0
Name: spectre
Version: 0.0.1
Summary: A dummy module for the preservation of the namespace.
Home-page: https://github.com/draperjames/
Author: James Draper
Author-email: james.draper@duke.edu
License: MIT
Keywords: Jupyter Notebook
Platform: UNKNOWN
Classifier: Development Status :: 3 - Alpha
Classifier: Intended Audience :: Developers
Classifier: Topic :: Software Development :: Build Tools
Classifier: License :: OSI Approved :: MIT License
Classifier: Programming Language :: Python :: 3.4
Classifier: Programming Language :: Python :: 3.5
